podcast_transcriber/__init__.py
podcast_transcriber/__main__.py
podcast_transcriber/cli.py
podcast_transcriber/orchestrator.py
podcast_transcriber/delivery/send_to_kindle.py
podcast_transcriber/exporters/__init__.py
podcast_transcriber/exporters/exporter.py
podcast_transcriber/exporters/themes.py
podcast_transcriber/flows/auto_run.py
podcast_transcriber/ingestion/feed.py
podcast_transcriber/kindle/epub_builder.py
podcast_transcriber/nlp/segment_topics.py
podcast_transcriber/services/__init__.py
podcast_transcriber/services/aws_transcribe.py
podcast_transcriber/services/base.py
podcast_transcriber/services/gcp_speech.py
podcast_transcriber/services/whisper.py
podcast_transcriber/storage/state.py
podcast_transcriber/templates/render.py
podcast_transcriber/utils/cache.py
podcast_transcriber/utils/downloader.py
podcast_transcriber/utils/textproc.py
podcast_transcriber-1.4.3.dist-info/licenses/LICENSE
podcast_transcriber-1.4.3.dist-info/METADATA
podcast_transcriber-1.4.3.dist-info/WHEEL
podcast_transcriber-1.4.3.dist-info/entry_points.txt
podcast_transcriber-1.4.3.dist-info/top_level.txt
podcast_transcriber-1.4.3.dist-info/RECORD
