Metadata-Version: 2.4
Name: podcast-transcriber
Version: 1.4.3
Summary: CLI tool to transcribe podcasts from a URL using pluggable services (Whisper, AWS, GCP).
Author: Johan Caripson
License: MIT
Classifier: Programming Language :: Python :: 3
Classifier: License :: OSI Approved :: MIT License
Classifier: Operating System :: OS Independent
Requires-Python: >=3.9
License-File: LICENSE
Requires-Dist: requests>=2.31.0
Provides-Extra: aws
Requires-Dist: boto3>=1.28.0; extra == "aws"
Provides-Extra: gcp
Requires-Dist: google-cloud-speech>=2.24.0; extra == "gcp"
Provides-Extra: whisper
Requires-Dist: openai-whisper>=20231117; extra == "whisper"
Provides-Extra: docs
Requires-Dist: mkdocs>=1.5.0; extra == "docs"
Requires-Dist: mkdocs-material>=9.1.0; extra == "docs"
Provides-Extra: dev
Requires-Dist: pytest>=7.4.0; extra == "dev"
Requires-Dist: black>=23.0.0; extra == "dev"
Requires-Dist: ruff>=0.4.0; extra == "dev"
Requires-Dist: pytest-cov>=4.1.0; extra == "dev"
Provides-Extra: export
Requires-Dist: fpdf2>=2.7.0; extra == "export"
Requires-Dist: ebooklib>=0.18; extra == "export"
Requires-Dist: Pillow>=9.5.0; extra == "export"
Provides-Extra: docx
Requires-Dist: python-docx>=0.8.11; extra == "docx"
Provides-Extra: orchestrator
Requires-Dist: PyYAML>=6.0; extra == "orchestrator"
Provides-Extra: ingest
Requires-Dist: feedparser>=6.0.10; extra == "ingest"
Provides-Extra: nlp
Requires-Dist: sentence-transformers>=2.2.2; extra == "nlp"
Provides-Extra: scheduler
Requires-Dist: APScheduler>=3.10.4; extra == "scheduler"
Provides-Extra: templates
Requires-Dist: Jinja2>=3.1.2; extra == "templates"
Provides-Extra: env
Requires-Dist: python-dotenv>=1.0.0; extra == "env"
Dynamic: license-file
